mahautils/__init__.py
mahautils/__main__.py
mahautils/py.typed
mahautils/multics/__init__.py
mahautils/multics/configfile.py
mahautils/multics/constants.py
mahautils/multics/exceptions.py
mahautils/multics/fluidprop.py
mahautils/multics/polygonfile.py
mahautils/multics/simresults.py
mahautils/multics/units.py
mahautils/multics/vtk.py
mahautils/multics/sim_results_exporter/__init__.py
mahautils/multics/sim_results_exporter/app.py
mahautils/multics/sim_results_exporter/constants.py
mahautils/multics/sim_results_exporter/export.py
mahautils/multics/sim_results_exporter/header.py
mahautils/multics/sim_results_exporter/io_utils.py
mahautils/multics/sim_results_exporter/store.py
mahautils/multics/sim_results_exporter/upload.py
mahautils/multics/sim_results_viewer/__init__.py
mahautils/multics/sim_results_viewer/app.py
mahautils/multics/sim_results_viewer/constants.py
mahautils/multics/sim_results_viewer/error_box.py
mahautils/multics/sim_results_viewer/header.py
mahautils/multics/sim_results_viewer/info.py
mahautils/multics/sim_results_viewer/load_files.py
mahautils/multics/sim_results_viewer/plotting.py
mahautils/multics/sim_results_viewer/store.py
mahautils/multics/sim_results_viewer/ui_elements.py
mahautils/multics/sim_results_viewer/panel/__init__.py
mahautils/multics/sim_results_viewer/panel/main_panel.py
mahautils/multics/sim_results_viewer/panel/settings_general.py
mahautils/multics/sim_results_viewer/panel/settings_x.py
mahautils/multics/sim_results_viewer/panel/settings_y.py
mahautils/multics/sim_results_viewer/panel/tab_data.py
mahautils/multics/sim_results_viewer/panel/tab_plot_settings.py
mahautils/multics/sim_results_viewer/panel/utils_generate_table.py
mahautils/shapes/__init__.py
mahautils/shapes/canvas.py
mahautils/shapes/layer.py
mahautils/shapes/plotting.py
mahautils/shapes/geometry/__init__.py
mahautils/shapes/geometry/circle.py
mahautils/shapes/geometry/geometry.py
mahautils/shapes/geometry/point.py
mahautils/shapes/geometry/point2D.py
mahautils-1.2.1.dist-info/LICENSE
mahautils-1.2.1.dist-info/METADATA
mahautils-1.2.1.dist-info/WHEEL
mahautils-1.2.1.dist-info/entry_points.txt
mahautils-1.2.1.dist-info/top_level.txt
mahautils-1.2.1.dist-info/RECORD
