Metadata-Version: 2.1
Name: mahautils
Version: 1.2.1
Summary: Python tools for research at the Maha Fluid Power Research Center
Home-page: https://github.com/nathan-hess/maha-research-utils
Author: Nathan Hess
License: AGPL-3.0
Project-URL: Documentation, https://mahautils.readthedocs.io
Requires-Python: >=3.8
License-File: LICENSE
Requires-Dist: dash >=2.8.1
Requires-Dist: dash-bootstrap-components >=1.4.0
Requires-Dist: matplotlib
Requires-Dist: numpy
Requires-Dist: packaging
Requires-Dist: pandas
Requires-Dist: plotly
Requires-Dist: pyxx
Requires-Dist: scipy
Requires-Dist: shapely
Requires-Dist: vtk
